demo/__init__.py
demo/local_settings.py
demo/sass_variables.py
demo/settings.py
demo/urls.py
demo/views.py
demo/wsgi.py
psu_upload/__init__.py
psu_upload/admin.py
psu_upload/apps.py
psu_upload/urls.py
psu_upload/views.py
psu_upload/classes/__init__.py
psu_upload/migrations/0001_initial.py
psu_upload/migrations/0002_auto_20200427_0733.py
psu_upload/migrations/0003_auto_20201118_1619.py
psu_upload/migrations/0004_auto_20201120_1353.py
psu_upload/migrations/0005_auto_20220720_1633.py
psu_upload/migrations/__init__.py
psu_upload/models/__init__.py
psu_upload/models/database_file.py
psu_upload/models/uploaded_file.py
psu_upload/services/__init__.py
psu_upload/services/retrieval_service.py
psu_upload/services/upload_service.py
psu_upload/templates/_dnd_input.html
psu_upload/templates/_upload_assets.html
psu_upload/templates/_upload_script.js
psu_upload/templates/_upload_style.css
psu_upload/templates/_upload_styles.html
psu_upload/templates/index.html
psu_upload/templates/read_sample.html
psu_upload/templates/upload_sample.html
psu_upload/templates/uploaded_sample.html
psu_upload/templates/psu/upload/_dnd_assets.html
psu_upload/templates/psu/upload/_dnd_input.html
psu_upload/templates/psu/upload/_dnd_resize.js
psu_upload/templates/psu/upload/_dnd_style.css
psu_upload/templates/psu/upload/_dnd_style.js
psu_upload/templates/psu/upload/_dnd_upload.js
psu_upload/templates/psu_upload/_dnd_assets.html
psu_upload/templates/psu_upload/_dnd_input.html
psu_upload/templates/psu_upload/_dnd_resize.js
psu_upload/templates/psu_upload/_dnd_style.css
psu_upload/templates/psu_upload/_dnd_style.js
psu_upload/templates/psu_upload/_dnd_upload.js
psu_upload/templatetags/__init__.py
psu_upload/templatetags/upload_taglib.py
psu_upload/tests/__init__.py
psu_upload/tests/test_applications.py
psu_upload-3.1.0.dist-info/METADATA
psu_upload-3.1.0.dist-info/WHEEL
psu_upload-3.1.0.dist-info/top_level.txt
psu_upload-3.1.0.dist-info/RECORD
