Metadata-Version: 2.1
Name: psu-upload
Version: 3.1.0
Summary: File uploads for PSU Django apps
Home-page: https://github.com/PSU-OIT-ARC/django-psu-upload
Author: Mike Gostomski
Author-email: mjg@pdx.edu
License: MIT License
Platform: UNKNOWN
Classifier: Framework :: Django :: 2.2
Classifier: License :: OSI Approved :: MIT License
Classifier: Operating System :: OS Independent
Classifier: Programming Language :: Python :: 3.6
Requires-Dist: boto3 (>=1.21.38)
Requires-Dist: django-storages (>=1.9.1)
Requires-Dist: psu-base (>=6.0.0)
Requires-Dist: python-magic (>=0.4.18)
